papers/__init__.py
papers/__version__.py
papers/cli.py
papers/papers.py
papers/templates/index.html
papers/utils/__init__.py
papers/utils/argparse.py
papers/utils/arxiv.py
papers/utils/bibtex.py
papers/utils/debug.py
papers/utils/formatters.py
papers/utils/imagemagick.py
papers-0.2.0.dist-info/LICENSE
papers-0.2.0.dist-info/METADATA
papers-0.2.0.dist-info/WHEEL
papers-0.2.0.dist-info/entry_points.txt
papers-0.2.0.dist-info/top_level.txt
papers-0.2.0.dist-info/RECORD
