Metadata-Version: 2.1
Name: papers
Version: 0.2.0
Summary: Simple reference manager in Python
Home-page: https://github.com/jan-matthis/papers
Author: Jan-Matthis Lueckmann
Author-email: mail@jan-matthis.de
License: MIT
Platform: UNKNOWN
Classifier: License :: OSI Approved :: MIT License
Classifier: Programming Language :: Python
Classifier: Programming Language :: Python :: 3.6
Classifier: Programming Language :: Python :: 3.7
Classifier: Programming Language :: Python :: 3.8
Classifier: Programming Language :: Python :: Implementation :: PyPy
Requires-Python: >=3.6.0
Requires-Dist: unidecode
Requires-Dist: jinja2
Requires-Dist: markdown2
Requires-Dist: pybtex
Requires-Dist: requests
Provides-Extra: dev
Requires-Dist: black ; extra == 'dev'
Requires-Dist: flake8 ; extra == 'dev'
Requires-Dist: isort ; extra == 'dev'
Requires-Dist: pytest ; extra == 'dev'
